{
  "#comment": "Sunken Ship night 4",
  "Information": {
    "uuid": "c58a208a-a5e3-4cfa-9bc3-cc7fbb08c2e3",
    "name": {
      "en": "Sunken Ship night 4",
      "zh-CN": "示例关卡1"
    },
    "Author": "Captian Impsanity",
    "AuthorLink": "@seal_enjoyer_de",
    "Introduction": {
      "en": "Sunken Ship night 4",
      "zh-CN": "这是一个示例关卡。"
    },
    "GameVersion": "0.1.13",
    "Version": "1.0",
    "CreatedAt": "2026-04-15",
    "UpdatedAt": "2026-04-15",
    "Difficulty": "Medium",
    "Category": "Survival"
  },
  "objects": [
    {
      "objclass": "LevelDefinition",
      "objdata": {
        "Description": "<PLAYERNAME>'s trip to the Sunken Ship",
        "LevelNumber": 4,
        "FirstIntroNarrative": "INTRO",
        "FirstOutroNarrative": "OUTRO",
        "ReplayIntroNarrative": "INTRO",
        "ReplayOutroNarrative": "OUTRO",
        "Loot": "RTID(DefaultLoot@LevelModules)",
        "Modules": [
          "RTID(ZombiesDeadWinCon@LevelModules)",
          "RTID(DefaultZombieWinCondition@LevelModules)",
          "RTID(FPP@CurrentLevel)",
          "RTID(SeedBank@CurrentLevel)",
          "RTID(LevelScheduler@CurrentLevel)",
          "RTID(NewWaves@CurrentLevel)",
          "RTID(ForzenPlantPlacement@CurrentLevel)",
          "RTID(PirateMowers@LevelModules)",
          "RTID(PiratePlanks@CurrentLevel)",
          "RTID(ChallengeModule@CurrentLevel)",
          "RTID(StandardIntro@LevelModules)",
          "RTID(Camera@LevelModules)"
        ],
        "Name": "Sunken Ship night 4",
        "NameMultiLanguage": {
          "en": "Sunken Ship night 4",
          "zh": "示例关卡I"
        },
        "WritenBy": "Captian impsanity",
        "NormalPresentTable": "egypt_normal_01",
        "ShinyPresentTable": "egypt_shiny_01",
        "StageModule": "RTID(PirateStage@LevelModules)"
      }
    },
    {
      "aliases": [
        "SeedBank"
      ],
      "objclass": "SeedBankProperties",
      "objdata": {
        "PlantExcludeList": [
          "blover",
          "hurrikale",
          "kernelpult"
        ],
        "PresetPlantList": [],
        "SelectionMethod": "chooser",
        "CardDecks": {
          "Recommended": [
            {
              "Name": {
                "en": "Reccomended",
                "zh": "接着推进！"
              },
              "Leader": 2,
              "Plants": [
                "sunflower",
                "buttercup",
                "cabbage",
                "wallnut",
                "cherry_bomb",
                "vamporcini",
                "bonkchoy"
              ]
            }
          ],
          "ChallengingLocked": false,
          "Challenging": [
            {
              "Name": {
                "en": "Challenge",
                "zh": "接着受挫"
              },
              "Leader": 1,
              "Plants": [
                "sunflower",
                "cherry_bomb",
                "bonkchoy",
                "cabbage",
                "repeater",
                "wallnut"
              ]
            }
          ]
        }
      }
    },
    {
      "objclass": "ThunderChargeWaveActionProps",
      "aliases": [
        "Thunder10times"
      ],
      "objdata": {
        "TimeBeforeFirst": {
          "Min": 1,
          "Max": 3
        },
        "TimeBetween": {
          "Min": 0.2,
          "Max": 3
        },
        "Thunders": [
          {
            "LinkedPlantCount": 1
          },
          {
            "LinkedPlantCount": 1
          },
          {
            "LinkedPlantCount": 1
          },
          {
            "LinkedPlantCount": 1
          },
          {
            "LinkedPlantCount": 1
          },
          {
            "LinkedPlantCount": 1
          },
          {
            "LinkedPlantCount": 1
          },
          {
            "LinkedPlantCount": 1
          },
          {
            "LinkedPlantCount": 1
          }
        ]
      }
    },
    {
      "aliases": [
        "MESSAGE_THUNDER"
      ],
      "objclass": "WaveWarningProps",
      "objdata": {
        "LabelR": 222,
        "LabelG": 255,
        "LabelB": 254,
        "LabelAInit": 4,
        "OutLineR": 255,
        "OutLineG": 252,
        "OutLineB": 255,
        "String": "Electric Burst !",
        "Sound": "Hugewave",
        "LabelTargetScale": 0.5,
        "LabelInitScale": 4,
        "Duration": 3.5,
        "InitTime": 0.33
      }
    },
    {
      "aliases": [
        "Camera"
      ],
      "objclass": "LawnCameraProps",
      "objdata": {
        "MultColor": {
          "r": 80,
          "g": 80,
          "b": 100,
          "a": 1
        },
        "AddColor": {
          "r": 0,
          "g": 0,
          "b": 0
        },
        "Chill": 0,
        "Gold": 0,
        "Saturation": 0.2
      },
      "DontClear": false,
      "//": "Dont change it yet.",
      "//OrthoHeight": 320,
      "Offset": {
        "x": 0,
        "y": 0
      }
    },
    {
      "aliases": [
        "PiratePlanks"
      ],
      "objclass": "PiratePlankProperties",
      "objdata": {
        "PlankRows": []
      }
    },
    {
      "aliases": [
        "NewWaves"
      ],
      "objclass": "WaveManagerModuleProperties",
      "objdata": {
        "DynamicZombies": [
          {},
          {},
          {},
          {
            "PointIncrementPerWave": 75,
            "StartingPoints": 75,
            "StartingWave": 1,
            "ZombiePool": [
              "RTID(seagull@ZombieTypes)",
              "RTID(pelican@ZombieTypes)"
            ]
          },
          {
            "PointIncrementPerWave": 100,
            "StartingPoints": 100,
            "StartingWave": 1,
            "ZombiePool": [
              "RTID(seagull@ZombieTypes)",
              "RTID(pelican@ZombieTypes)"
            ]
          },
          {
            "PointIncrementPerWave": 125,
            "StartingPoints": 125,
            "StartingWave": 1,
            "ZombiePool": [
              "RTID(seagull@ZombieTypes)",
              "RTID(pelican@ZombieTypes)"
            ]
          },
          {
            "PointIncrementPerWave": 175,
            "StartingPoints": 175,
            "StartingWave": 1,
            "ZombiePool": [
              "RTID(seagull@ZombieTypes)",
              "RTID(pelican@ZombieTypes)"
            ]
          }
        ],
        "WaveManagerProps": "RTID(WaveManagerProps@CurrentLevel)"
      }
    },
    {
      "aliases": [
        "WaveManagerProps"
      ],
      "objclass": "WaveManagerProperties",
      "objdata": {
        "SuppressFlagZombie": true,
        "FlagWaveVeteranOverrideTypes": [
          1,
          1
        ],
        "FlagWaveInterval": 6,
        "WaveCount": 12,
        "Waves": [
          [
            "RTID(Wave1@CurrentLevel)"
          ],
          [
            "RTID(Wave2@CurrentLevel)"
          ],
          [
            "RTID(Wave3@CurrentLevel)",
            "RTID(Thunder10times@CurrentLevel)",
            "RTID(MESSAGE_THUNDER@CurrentLevel)"
          ],
          [
            "RTID(Wave4@CurrentLevel)"
          ],
          [
            "RTID(Wave5@CurrentLevel)"
          ],
          [
            "RTID(Wave6@CurrentLevel)",
            "RTID(Thunder10times@CurrentLevel)",
            "RTID(MESSAGE_THUNDER@CurrentLevel)"
          ],
          [
            "RTID(Wave7@CurrentLevel)"
          ],
          [
            "RTID(Wave8@CurrentLevel)"
          ],
          [
            "RTID(Wave9@CurrentLevel)",
            "RTID(Thunder10times@CurrentLevel)",
            "RTID(MESSAGE_THUNDER@CurrentLevel)"
          ],
          [
            "RTID(Wave10@CurrentLevel)"
          ],
          [
            "RTID(Wave11@CurrentLevel)"
          ],
          [
            "RTID(Wave12@CurrentLevel)",
            "RTID(Thunder10times@CurrentLevel)",
            "RTID(MESSAGE_THUNDER@CurrentLevel)"
          ]
        ]
      }
    },
    {
      "aliases": [
        "Wave1"
      ],
      "objclass": "SpawnZombiesJitteredWaveActionProps",
      "objdata": {
        "Zombies": [
          {
            "Type": "RTID(pelican@ZombieTypes)"
          }
        ]
      }
    },
    {},
    {
      "aliases": [
        "Wave2"
      ],
      "objclass": "SpawnZombiesJitteredWaveActionProps",
      "objdata": {
        "Zombies": [
          {
            "Type": "RTID(pelican@ZombieTypes)"
          }
        ]
      }
    },
    {},
    {
      "aliases": [
        "Wave3"
      ],
      "objclass": "SpawnZombiesJitteredWaveActionProps",
      "objdata": {
        "Zombies": [
          {
            "Type": "RTID(pelican@ZombieTypes)"
          },
          {
            "Type": "RTID(seagull@ZombieTypes)"
          }
        ]
      }
    },
    {
      "aliases": [
        "Wave4"
      ],
      "objclass": "SpawnZombiesJitteredWaveActionProps",
      "objdata": {
        "Zombies": [
          {
            "Type": "RTID(seagull@ZombieTypes)"
          },
          {
            "Type": "RTID(pelican@ZombieTypes)"
          }
        ]
      }
    },
    {
      "aliases": [
        "Wave5"
      ],
      "objclass": "SpawnZombiesJitteredWaveActionProps",
      "objdata": {
        "Zombies": [
          {
            "Type": "RTID(pelican@ZombieTypes)"
          },
          {
            "Type": "RTID(pelican@ZombieTypes)"
          },
          {
            "Type": "RTID(pelican@ZombieTypes)"
          }
        ]
      }
    },
    {
      "aliases": [
        "Wave6"
      ],
      "objclass": "SpawnZombiesJitteredWaveActionProps",
      "objdata": {
        "Zombies": [
          {
            "Type": "RTID(pelican@ZombieTypes)"
          },
          {
            "Type": "RTID(seagull@ZombieTypes)"
          },
          {
            "Type": "RTID(seagull@ZombieTypes)"
          }
        ]
      }
    },
    {
      "aliases": [
        "Wave7"
      ],
      "objclass": "SpawnZombiesJitteredWaveActionProps",
      "objdata": {
        "Zombies": [
          {
            "Type": "RTID(pelican@ZombieTypes)"
          },
          {
            "Type": "RTID(seagull@ZombieTypes)"
          }
        ]
      }
    },
    {
      "aliases": [
        "Wave8"
      ],
      "objclass": "SpawnZombiesJitteredWaveActionProps",
      "objdata": {
        "Zombies": [
          {
            "Type": "RTID(seagull@ZombieTypes)"
          },
          {
            "Type": "RTID(pelican@ZombieTypes)"
          },
          {
            "Type": "RTID(pelican@ZombieTypes)"
          },
          {
            "Type": "RTID(pelican@ZombieTypes)"
          }
        ]
      }
    },
    {
      "aliases": [
        "Wave9"
      ],
      "objclass": "SpawnZombiesJitteredWaveActionProps",
      "objdata": {
        "Zombies": [
          {
            "Type": "RTID(seagull@ZombieTypes)"
          },
          {
            "Type": "RTID(seagull@ZombieTypes)"
          },
          {
            "Type": "RTID(seagull@ZombieTypes)"
          },
          {
            "Type": "RTID(pelican@ZombieTypes)"
          }
        ]
      }
    },
    {
      "aliases": [
        "Wave10"
      ],
      "objclass": "SpawnZombiesJitteredWaveActionProps",
      "objdata": {
        "Zombies": [
          {
            "Type": "RTID(seagull@ZombieTypes)"
          },
          {
            "Type": "RTID(seagull@ZombieTypes)"
          },
          {
            "Type": "RTID(seagull@ZombieTypes)"
          },
          {
            "Type": "RTID(seagull@ZombieTypes)"
          }
        ]
      }
    },
    {
      "aliases": [
        "Wave11"
      ],
      "objclass": "SpawnZombiesJitteredWaveActionProps",
      "objdata": {
        "Zombies": [
          {
            "Type": "RTID(pelican@ZombieTypes)"
          },
          {
            "Type": "RTID(pelican@ZombieTypes)"
          },
          {
            "Type": "RTID(pelican@ZombieTypes)"
          },
          {
            "Type": "RTID(pelican@ZombieTypes)"
          },
          {
            "Type": "RTID(pelican@ZombieTypes)"
          }
        ]
      }
    },
    {
      "aliases": [
        "Wave12"
      ],
      "objclass": "SpawnZombiesJitteredWaveActionProps",
      "objdata": {
        "Zombies": [
          {
            "Type": "RTID(pelican@ZombieTypes)"
          },
          {
            "Type": "RTID(pelican@ZombieTypes)"
          },
          {
            "Type": "RTID(seagull@ZombieTypes)"
          },
          {
            "Type": "RTID(seagull@ZombieTypes)"
          },
          {
            "Type": "RTID(seagull@ZombieTypes)"
          }
        ]
      }
    }
  ],
  "version": 1
}